demo_extractors/__init__.py
demo_extractors/elfy.py
demo_extractors/limit_other.py
demo_extractors/nothing.py
demo_extractors/requirements.txt
demo_extractors/shared.py
demo_extractors/terminator.py
demo_extractors/complex/__init__.py
demo_extractors/complex/complex.py
demo_extractors/complex/complex_utils.py
extractor_setup/maco/__init__.py
extractor_setup/maco/base_test.py
extractor_setup/maco/cli.py
extractor_setup/maco/collector.py
extractor_setup/maco/exceptions.py
extractor_setup/maco/extractor.py
extractor_setup/maco/utils.py
extractor_setup/maco/yara.py
extractor_setup/maco/model/__init__.py
extractor_setup/maco/model/model.py
maco/__init__.py
maco/base_test.py
maco/cli.py
maco/collector.py
maco/exceptions.py
maco/extractor.py
maco/utils.py
maco/yara.py
maco/model/__init__.py
maco/model/model.py
maco-1.2.19.dist-info/licenses/LICENSE.md
model_setup/maco/__init__.py
model_setup/maco/base_test.py
model_setup/maco/cli.py
model_setup/maco/collector.py
model_setup/maco/exceptions.py
model_setup/maco/extractor.py
model_setup/maco/utils.py
model_setup/maco/yara.py
model_setup/maco/model/__init__.py
model_setup/maco/model/model.py
pipelines/publish.yaml
pipelines/test.yaml
tests/data/example.txt.cart
tests/data/trigger_complex.txt
tests/data/trigger_complex.txt.cart
tests/extractors/__init__.py
tests/extractors/basic.py
tests/extractors/basic_longer.py
tests/extractors/test_basic.py
tests/extractors/bob/__init__.py
tests/extractors/bob/bob.py
tests/extractors/import_rewriting/__init__.py
tests/extractors/import_rewriting/importer.py
maco-1.2.19.dist-info/METADATA
maco-1.2.19.dist-info/WHEEL
maco-1.2.19.dist-info/entry_points.txt
maco-1.2.19.dist-info/top_level.txt
maco-1.2.19.dist-info/RECORD
