Metadata-Version: 2.4
Name: maco
Version: 1.2.19
Summary: Maco is a framework for creating and using malware configuration extractors.
Author: sl-govau
Maintainer: cccs-rs
License: MIT License
Project-URL: Repository, https://github.com/CybercentreCanada/Maco
Project-URL: Issues, https://github.com/CybercentreCanada/Maco/issues
Classifier: Development Status :: 5 - Production/Stable
Classifier: Intended Audience :: Developers
Classifier: Topic :: Software Development :: Libraries :: Python Modules
Classifier: License :: OSI Approved :: MIT License
Classifier: Programming Language :: Python :: 3.8
Classifier: Programming Language :: Python :: 3.9
Classifier: Programming Language :: Python :: 3.10
Classifier: Programming Language :: Python :: 3.11
Classifier: Programming Language :: Python :: 3.12
Requires-Python: >=3.8
License-File: LICENSE.md
Requires-Dist: cart
Requires-Dist: pydantic>=2.0.0
Requires-Dist: tomli>=1.1.0; python_version < "3.11"
Requires-Dist: uv
Requires-Dist: yara-x
Requires-Dist: multiprocess>=0.70.17
Dynamic: license-file
